cathodic_report-0.1.9.dist-info/METADATA
cathodic_report-0.1.9.dist-info/WHEEL
cathodic_report-0.1.9.dist-info/entry_points.txt
cathodic_report/__init__.py
cathodic_report/checker.py
cathodic_report/compress.py
cathodic_report/draw.py
cathodic_report/file.py
cathodic_report/funcs.py
cathodic_report/graph.py
cathodic_report/output/forms.py
cathodic_report/report.py
cathodic_report/table.py
cathodic_report/types.py
cathodic_report/utils.py
cathodic_report/wordfile/__init__.py
cathodic_report/wordfile/append.py
cathodic_report/wordfile/font.py
cathodic_report/wordfile/forms.py
cathodic_report/wordfile/render.py
cathodic_report/wordfile/test_font.py
cathodic_report/wordfile/utils.py
cathodic_report-0.1.9.dist-info/RECORD
