Metadata-Version: 2.1
Name: cathodic-report
Version: 0.1.9
Summary: Cathodic protection report generator
Author-Email: svtter <svtter@qq.com>
License: NOT OPEN SOURCE
Requires-Python: ==3.11.*
Requires-Dist: pydantic>=2.9.2
Requires-Dist: matplotlib>=3.9.2
Requires-Dist: python-docx>=1.1.2
Requires-Dist: docxtpl>=0.18.0
Requires-Dist: httpx>=0.27.2
Requires-Dist: mplfonts>=0.0.10
